orchestration_commons
