Metadata-Version: 1.1
Name: orchestration-commons
Version: 0.1.3.1
Summary: Common functions used in orchestrators.
Home-page: https://github.com/adminMesfix/orchestration-commons
Author: Jesus Martinez
Author-email: jesus.a.martinez.v@gmail.com
License: UNKNOWN
Download-URL: https://github.com/adminMesfix/orchestration-commons/tarball/0.1.3.1
Keywords: orchestrator,orchestration,commons
Platform: UNKNOWN
